Metadata-Version: 2.1
Name: py-auto-di
Version: 0.1.2
Summary: Lightweight, automatic Python DI library
Home-page: https://github.com/cmstead/py-auto-di#readme
Author: Chris Stead
Author-email: cmstead@gmail.com
License: MIT
Platform: any
Classifier: License :: OSI Approved :: MIT License
Classifier: Programming Language :: Python :: 3
Classifier: Programming Language :: Python :: 3.8
